{
  "search_metadata": {
    "id": "69cd8707fda607d7b61157d0",
    "status": "Success",
    "json_endpoint": "https://serpapi.com/searches/FhIVhwLufOAwk8lYTDaUTA/69cd8707fda607d7b61157d0.json",
    "created_at": "2026-04-01 20:58:47 UTC",
    "processed_at": "2026-04-01 20:58:47 UTC",
    "amazon_product_url": "https://www.amazon.com/dp/AIRTAG2G1PK-TBD/?",
    "raw_html_file": "https://serpapi.com/searches/FhIVhwLufOAwk8lYTDaUTA/69cd8707fda607d7b61157d0.html",
    "total_time_taken": 8.78
  },
  "search_parameters": {
    "engine": "amazon_product",
    "asin": "AIRTAG2G1PK-TBD",
    "amazon_domain": "amazon.com",
    "device": "desktop"
  },
  "search_information": {
    "organic_results_state": "Fully empty"
  },
  "error": "Amazon Product hasn't returned any results for this query."
}