{
  "search_metadata": {
    "id": "69db51ec6feec4e2bfbbb7be",
    "status": "Success",
    "json_endpoint": "https://serpapi.com/searches/wRkfp45jPwnNwlrPu2IH8w/69db51ec6feec4e2bfbbb7be.json",
    "created_at": "2026-04-12 08:03:56 UTC",
    "processed_at": "2026-04-12 08:03:56 UTC",
    "amazon_product_url": "https://www.amazon.com/dp/B0FPF6VZJ7/?",
    "raw_html_file": "https://serpapi.com/searches/wRkfp45jPwnNwlrPu2IH8w/69db51ec6feec4e2bfbbb7be.html",
    "total_time_taken": 8.3
  },
  "search_parameters": {
    "engine": "amazon_product",
    "asin": "B0FPF6VZJ7",
    "amazon_domain": "amazon.com",
    "device": "desktop"
  },
  "product_results": {
    "asin": "B0FPF6VZJ7",
    "title": "Collapsible Dog Crate for Medium/Small Dogs - 28\" L Foldable Dog Cage No-Tool Assembly, Travel Dog Crate with 2 Wheels - Easy to Carry, Space-Saving, Indoor Outdoor Use",
    "link": "https://www.amazon.com/Collapsible-Crate-Medium-Small-Dogs/dp/B0FPF6VZJ7/",
    "link_clean": "https://www.amazon.com/dp/B0FPF6VZJ7/",
    "serpapi_link": "https://serpapi.com/search.json?amazon_domain=amazon.com&asin=B0FPF6VZJ7&device=desktop&engine=amazon_product",
    "badges": [
      "Amazon's Choice"
    ],
    "variants": [
      {
        "title": "Size",
        "items": [
          {
            "position": 1,
            "asin": "B0FPF6VZJ7",
            "name": "27.96\"(L)X18.3\"(W)X20.87(H)",
            "selected": true,
            "serpapi_link": "https://serpapi.com/search.json?amazon_domain=amazon.com&asin=B0FPF6VZJ7&device=desktop&engine=amazon_product"
          },
          {
            "position": 2,
            "asin": "B0FPF8VSY9",
            "name": "36.4\"(L)x22.84\"(W)25.8\"(H)",
            "serpapi_link": "https://serpapi.com/search.json?amazon_domain=amazon.com&asin=B0FPF8VSY9&device=desktop&engine=amazon_product"
          }
        ]
      }
    ],
    "brand": "Visit the Gardner Pet Store",
    "thumbnail": "https://m.media-amazon.com/images/I/712Iv0QSn0L._AC_SY300_SX300_QL70_FMwebp_.jpg",
    "thumbnails": [
      "https://m.media-amazon.com/images/I/712Iv0QSn0L._AC_SL1500_.jpg",
      "https://m.media-amazon.com/images/I/71gxqf2ODHL._AC_SL1500_.jpg",
      "https://m.media-amazon.com/images/I/71Z2K5857pL._AC_SL1500_.jpg",
      "https://m.media-amazon.com/images/I/712S7cjIyQL._AC_SL1500_.jpg",
      "https://m.media-amazon.com/images/I/71KE4xtj5HL._AC_SL1500_.jpg",
      "https://m.media-amazon.com/images/I/719lIb1KEKL._AC_SL1500_.jpg",
      "https://m.media-amazon.com/images/I/71aI9J0cZ+L._AC_SL1500_.jpg",
      "https://m.media-amazon.com/images/I/719dH+NIxAL._AC_SL1500_.jpg"
    ],
    "rating": 4.9,
    "reviews": 48,
    "bought_last_month": "300+ bought in past month",
    "price": "$99.99",
    "extracted_price": 99.99,
    "offers": [
      "Save 5%"
    ],
    "prime": true,
    "delivery": [
      "FREE delivery Friday, April 17",
      "Or Prime members get FREE delivery Tomorrow, April 13. Join Prime"
    ],
    "stock": "In Stock"
  },
  "purchase_options": {
    "single_offer": {
      "price": "$99.99",
      "extracted_price": 99.99,
      "delivery": [
        "FREE delivery Friday, April 17",
        "Or Prime members get FREE delivery Tomorrow, April 13. Join Prime"
      ],
      "stock": "In Stock",
      "features": {
        "ships_from": {
          "text": "Amazon",
          "details": {
            "heading": "Ships from",
            "content": "Amazon"
          }
        },
        "sold_by": {
          "text": "Gardner Pet Official",
          "details": {
            "heading": "Sold by",
            "content": "Gardner Pet Official"
          },
          "link": {
            "text": "Gardner Pet Official",
            "link": "https://www.amazon.com/gp/help/seller/at-a-glance.html/ref=dp_merchant_link?ie=UTF8&seller=A15OHL7UF1C0FB&asin=B0FPF6VZJ7&ref_=dp_merchant_link&isAmazonFulfilled=1"
          }
        },
        "returns": {
          "text": "FREE 30-day refund/replacement",
          "details": {
            "heading": "FREE 30-day refund/replacement"
          },
          "link": {
            "text": "See exceptions",
            "link": "https://www.amazon.com/gp/help/customer/display.html/?nodeId=GKQNFKFK5CF3C54B"
          }
        },
        "packaging": {
          "text": "Ships in product packaging",
          "details": {
            "heading": "Ships in product packaging",
            "content": "This item has been tested to certify it can ship safely in its original box or bag to avoid unnecessary packaging. Since 2015, we have reduced the weight of outbound packaging per shipment by 41% on average, that’s over 2 million tons of packaging material.If you still require Amazon packaging for this item, choose \"Ship in Amazon packaging\" at checkout. Learn more"
          },
          "link": {
            "text": "Learn more",
            "link": "https://www.amazon.com/sipp_home"
          }
        }
      }
    }
  },
  "item_specifications": {
    "brand": "Gardner Pet",
    "product_dimensions": "27.96\"L x 18.3\"W x 20.87\"H",
    "material": "50% Recycled pre-consumer Metal (RM0248) + 48%Polypropylene (RM0202) +2% Polyethylene terephthalate (PET) (RM0194)\"",
    "specific_uses_for_product": "Indoor, Outdoor",
    "special_feature": "Collapsible, Easy to Use, Hard Case, Heavy Duty, Portable"
  },
  "about_item": [
    "Easy to Assemble: The one-piece folding dog box furniture eliminates the need for complex assembly. You can create a comfortable haven for your pet set up and fold down the crate in seconds with no tools required. Enjoy a wonderful life with your furry good friend!",
    "Space-Saving & Easy Mobility: This collapsible dog crate features a innovative foldable design, allowing it to be stored flat when not in use. Equipped with two smooth-rolling wheels and sturdy handles on both sides, this pet crate offers effortless mobility. Move your dog cage around the house or during travel with minimal effort",
    "Safe & Reliable: Gardner Pet pet kennel Features squeeze-latch locks on the door for quick and secure closure. allowing your furry friends to stay safely inside while also being friendly to the fingers of pet guardians. These locks are easy for owners to operate but prevent clever dogs from opening them.Our curved corners help prevent squeezing and the sinking of the chin and claws, and the rounded corners eliminate sharp edges",
    "Long-lasting Dog House: Composed of high-quality PE and strong metal wire, the indoor dog house is both functional and aesthetically pleasing for modern homes, providing your pet with a long-lasting, stable and safe resting place",
    "Multi-functional Dog Cage furniture: Modern style, suitable for any home decoration, whether as a cozy indoor dog house, a travel crate for road trips, or a temporary containment space outdoors",
    "Quality & Care: Gardner Pet is committed to creating meticulously designed pet products, prioritizing safety, comfort and convenience. Our mission is to improve the lives of pets and their owners through high-quality, innovative solutions that stand the test of time"
  ],
  "bought_together": [
    {
      "position": 1,
      "title": "Collapsible Dog Crate for Medium/Small Dogs - 28\" L Foldable Dog Cage No-Tool Assembly, Travel Dog Crate with 2 Wheels - Easy to Carry, Space-Saving, Indoor Outdoor Use",
      "thumbnail": "https://images-na.ssl-images-amazon.com/images/I/712Iv0QSn0L._AC_UL116_SR116,116_.jpg",
      "price": "$99.99",
      "extracted_price": 99.99,
      "delivery": [
        "Get it as soon as Friday, Apr 17"
      ],
      "stock": "In Stock"
    },
    {
      "position": 2,
      "title": "Dog Bed Mat – Soft & Comfortable Dog Kennel Pad for Crate – Durable Crate Bed & Mat for Dogs & Cats – Ideal for Crate, Kennel, and Home Use",
      "link": "https://www.amazon.com/Dog-Bed-Mat-Comfortable-Durable/dp/B0DHVJPH6T/ref=pd_bxgy_thbs_d_sccl_1/138-4545753-7583228?pd_rd_w=7ZWP9&content-id=amzn1.sym.9bef5913-5870-4504-8883-3ba89d7f8e39&pf_rd_p=9bef5913-5870-4504-8883-3ba89d7f8e39&pf_rd_r=7G2FD7MKN8KHFEPRZ04K&pd_rd_wg=KY4uL&pd_rd_r=ab42157f-1806-47ab-81af-017f1ceb4f98&pd_rd_i=B0DHVJPH6T&psc=1",
      "asin": "B0DHVJPH6T",
      "link_clean": "https://www.amazon.com/Dog-Bed-Mat-Comfortable-Durable/dp/B0DHVJPH6T/",
      "serpapi_link": "https://serpapi.com/search.json?amazon_domain=amazon.com&asin=B0DHVJPH6T&device=desktop&engine=amazon_product",
      "thumbnail": "https://images-na.ssl-images-amazon.com/images/I/81sXhmUmZVL._AC_UL116_SR116,116_.jpg",
      "price": "$9.99",
      "extracted_price": 9.99,
      "price_unit": "$9.99/count",
      "extracted_price_unit": 9.99,
      "delivery": [
        "Get it as soon as Friday, Apr 17"
      ],
      "stock": "In Stock"
    }
  ],
  "related_products": [
    {
      "position": 1,
      "asin": "B07GKYW3KR",
      "title": "SportPet Airline Compliant MEDIUM 24.25\" Travel Dog Kennel-Durable Plastic Airline Pet Carrier w/Removable Wheels & Food Bowls, Collapsible Indoor/Outdoor Dog Kennel, Dogs up to 23\"L & 15\"H-Cream/Gray",
      "link": "https://www.amazon.com/sspa/click?ie=UTF8&spc=MTo2NzE0MjY4MzIxMDk0MTM5OjE3NzU5ODEwNDM6c3BfZGV0YWlsOjMwMTIxODQ1NTgzNDQwMjo6Ojo&url=%2Fdp%2FB07GKYW3KR%2Fref%3Dsspa_dk_detail_0%3Fpsc%3D1%26pd_rd_i%3DB07GKYW3KR%26pd_rd_w%3D1N3gE%26content-id%3Damzn1.sym.613a5a0c-ad86-44dc-b9ed-5da62fb83b9e%26pf_rd_p%3D613a5a0c-ad86-44dc-b9ed-5da62fb83b9e%26pf_rd_r%3D7G2FD7MKN8KHFEPRZ04K%26pd_rd_wg%3DKY4uL%26pd_rd_r%3Dab42157f-1806-47ab-81af-017f1ceb4f98%26sp_csd%3Dd2lkZ2V0TmFtZT1zcF9kZXRhaWw",
      "link_clean": "https://www.amazon.com/dp/B07GKYW3KR/",
      "serpapi_link": "https://serpapi.com/search.json?amazon_domain=amazon.com&asin=B07GKYW3KR&device=desktop&engine=amazon_product",
      "sponsored": true,
      "thumbnail": "https://m.media-amazon.com/images/I/71BtFj+Mi9L._AC_UF480,480_SR480,480_.jpg",
      "rating": 4.5,
      "reviews": 6147,
      "discount": "-13%",
      "price": "$79.99",
      "extracted_price": 79.99,
      "old_price": "$92.00",
      "extracted_old_price": 92,
      "prime": true
    },
    {
      "position": 2,
      "asin": "B000QFT1RC",
      "title": "MidWest Homes for Pets 42-Inch iCrate for Large Breeds, 71-90 lbs, Double Door Folding Dog Crate with Divider Panel, Leak-Proof Tray & Secure Latches, Portable, Durable & Easy to Assemble",
      "link": "https://www.amazon.com/sspa/click?ie=UTF8&spc=MTo2NzE0MjY4MzIxMDk0MTM5OjE3NzU5ODEwNDM6c3BfZGV0YWlsOjIwMDAwNDk0NjMxNzY2MTo6Ojo&url=%2Fdp%2FB000QFT1RC%2Fref%3Dsspa_dk_detail_1%3Fpsc%3D1%26pd_rd_i%3DB000QFT1RC%26pd_rd_w%3D1N3gE%26content-id%3Damzn1.sym.613a5a0c-ad86-44dc-b9ed-5da62fb83b9e%26pf_rd_p%3D613a5a0c-ad86-44dc-b9ed-5da62fb83b9e%26pf_rd_r%3D7G2FD7MKN8KHFEPRZ04K%26pd_rd_wg%3DKY4uL%26pd_rd_r%3Dab42157f-1806-47ab-81af-017f1ceb4f98%26sp_csd%3Dd2lkZ2V0TmFtZT1zcF9kZXRhaWw",
      "link_clean": "https://www.amazon.com/dp/B000QFT1RC/",
      "serpapi_link": "https://serpapi.com/search.json?amazon_domain=amazon.com&asin=B000QFT1RC&device=desktop&engine=amazon_product",
      "sponsored": true,
      "badges": [
        "Amazon's Choice"
      ],
      "thumbnail": "https://m.media-amazon.com/images/I/916OE0sVPqL._AC_UF480,480_SR480,480_.jpg",
      "rating": 4.7,
      "reviews": 80142,
      "price": "$84.99",
      "extracted_price": 84.99,
      "prime": true
    },
    {
      "position": 3,
      "asin": "B098K6SXST",
      "title": "DONORO Dog Crates for Small Size Dogs Indoor Double Door Dog Kennels & Houses for Puppy and Cats, Collapsible Metal Contour Dog Cages (Brown, 24.0\" L x 18.0\" W x 20.0\" H)",
      "link": "https://www.amazon.com/sspa/click?ie=UTF8&spc=MTo2NzE0MjY4MzIxMDk0MTM5OjE3NzU5ODEwNDM6c3BfZGV0YWlsOjIwMDA5ODU3NDc5NDkxMTo6Ojo&url=%2Fdp%2FB098K6SXST%2Fref%3Dsspa_dk_detail_2%3Fpsc%3D1%26pd_rd_i%3DB098K6SXST%26pd_rd_w%3D1N3gE%26content-id%3Damzn1.sym.613a5a0c-ad86-44dc-b9ed-5da62fb83b9e%26pf_rd_p%3D613a5a0c-ad86-44dc-b9ed-5da62fb83b9e%26pf_rd_r%3D7G2FD7MKN8KHFEPRZ04K%26pd_rd_wg%3DKY4uL%26pd_rd_r%3Dab42157f-1806-47ab-81af-017f1ceb4f98%26sp_csd%3Dd2lkZ2V0TmFtZT1zcF9kZXRhaWw",
      "link_clean": "https://www.amazon.com/dp/B098K6SXST/",
      "serpapi_link": "https://serpapi.com/search.json?amazon_domain=amazon.com&asin=B098K6SXST&device=desktop&engine=amazon_product",
      "sponsored": true,
      "thumbnail": "https://m.media-amazon.com/images/I/717rs4t6CSL._AC_UF480,480_SR480,480_.jpg",
      "rating": 4.6,
      "reviews": 1039,
      "price": "$49.97",
      "extracted_price": 49.97,
      "prime": true
    },
    {
      "position": 4,
      "asin": "B0D8339XDM",
      "title": "Veraste 33\" L x 25\" W x 25\" H Collapsible Travel Dog Crate, Portable Soft Dog Kennel for Medium Large Dogs up to 60 lbs, 4-Door Foldable Travel Crate with Durable Mesh & Storage BagGreen",
      "link": "https://www.amazon.com/sspa/click?ie=UTF8&spc=MTo2NzE0MjY4MzIxMDk0MTM5OjE3NzU5ODEwNDM6c3BfZGV0YWlsOjMwMDg3NzQ4MTc2NjkwMjo6Ojo&url=%2Fdp%2FB0D8339XDM%2Fref%3Dsspa_dk_detail_3%3Fpsc%3D1%26pd_rd_i%3DB0D8339XDM%26pd_rd_w%3D1N3gE%26content-id%3Damzn1.sym.613a5a0c-ad86-44dc-b9ed-5da62fb83b9e%26pf_rd_p%3D613a5a0c-ad86-44dc-b9ed-5da62fb83b9e%26pf_rd_r%3D7G2FD7MKN8KHFEPRZ04K%26pd_rd_wg%3DKY4uL%26pd_rd_r%3Dab42157f-1806-47ab-81af-017f1ceb4f98%26sp_csd%3Dd2lkZ2V0TmFtZT1zcF9kZXRhaWw",
      "link_clean": "https://www.amazon.com/dp/B0D8339XDM/",
      "serpapi_link": "https://serpapi.com/search.json?amazon_domain=amazon.com&asin=B0D8339XDM&device=desktop&engine=amazon_product",
      "sponsored": true,
      "thumbnail": "https://m.media-amazon.com/images/I/71o-s3dAlCL._AC_UF480,480_SR480,480_.jpg",
      "rating": 3.8,
      "reviews": 479,
      "discount": "-18%",
      "price": "$89.99",
      "extracted_price": 89.99,
      "price_unit": "$89.99 / count",
      "extracted_price_unit": 89.99,
      "old_price": "$109.99",
      "extracted_old_price": 109.99,
      "prime": true
    },
    {
      "position": 5,
      "asin": "B09D8KSWTV",
      "title": "KindTail PAWD Collapsible Puppy and Dog Crate + Washable Bed - Stylish Pet Kennel with Comfortable Pad - Safe Indoor Set - Lightweight, Compact & Portable for Travel - Small White",
      "link": "https://www.amazon.com/sspa/click?ie=UTF8&spc=MTo2NzE0MjY4MzIxMDk0MTM5OjE3NzU5ODEwNDM6c3BfZGV0YWlsOjMwMTIzNDk3MTg3MjAwMjo6Ojo&url=%2Fdp%2FB09D8KSWTV%2Fref%3Dsspa_dk_detail_4%3Fpsc%3D1%26pd_rd_i%3DB09D8KSWTV%26pd_rd_w%3D1N3gE%26content-id%3Damzn1.sym.613a5a0c-ad86-44dc-b9ed-5da62fb83b9e%26pf_rd_p%3D613a5a0c-ad86-44dc-b9ed-5da62fb83b9e%26pf_rd_r%3D7G2FD7MKN8KHFEPRZ04K%26pd_rd_wg%3DKY4uL%26pd_rd_r%3Dab42157f-1806-47ab-81af-017f1ceb4f98%26sp_csd%3Dd2lkZ2V0TmFtZT1zcF9kZXRhaWw",
      "link_clean": "https://www.amazon.com/dp/B09D8KSWTV/",
      "serpapi_link": "https://serpapi.com/search.json?amazon_domain=amazon.com&asin=B09D8KSWTV&device=desktop&engine=amazon_product",
      "sponsored": true,
      "thumbnail": "https://m.media-amazon.com/images/I/61jTpS6FsTL._AC_UF480,480_SR480,480_.jpg",
      "rating": 4.1,
      "reviews": 69,
      "price": "$129.99",
      "extracted_price": 129.99,
      "price_unit": "$129.99 / count",
      "extracted_price_unit": 129.99,
      "prime": true
    },
    {
      "position": 6,
      "asin": "B0FDPVJH5Q",
      "title": "ZOMISIA Collapsible Dog Crate for Dogs - 28\" L Heavy Duty Dog Kennel No Tools Required with 4 Sides Steel Foldable Cage for Dogs Indoor Furniture, Portable Carrier with 2 Smooth Wheels, Beige",
      "link": "https://www.amazon.com/sspa/click?ie=UTF8&spc=MTo2NzE0MjY4MzIxMDk0MTM5OjE3NzU5ODEwNDM6c3BfZGV0YWlsOjMwMTEzMTk4OTA0NzMwMjo6Ojo&url=%2Fdp%2FB0FDPVJH5Q%2Fref%3Dsspa_dk_detail_5%3Fpsc%3D1%26pd_rd_i%3DB0FDPVJH5Q%26pd_rd_w%3D1N3gE%26content-id%3Damzn1.sym.613a5a0c-ad86-44dc-b9ed-5da62fb83b9e%26pf_rd_p%3D613a5a0c-ad86-44dc-b9ed-5da62fb83b9e%26pf_rd_r%3D7G2FD7MKN8KHFEPRZ04K%26pd_rd_wg%3DKY4uL%26pd_rd_r%3Dab42157f-1806-47ab-81af-017f1ceb4f98%26sp_csd%3Dd2lkZ2V0TmFtZT1zcF9kZXRhaWw",
      "link_clean": "https://www.amazon.com/dp/B0FDPVJH5Q/",
      "serpapi_link": "https://serpapi.com/search.json?amazon_domain=amazon.com&asin=B0FDPVJH5Q&device=desktop&engine=amazon_product",
      "sponsored": true,
      "badges": [
        "Limited time deal"
      ],
      "thumbnail": "https://m.media-amazon.com/images/I/81YdRCpJqKL._AC_UF480,480_SR480,480_.jpg",
      "rating": 4.6,
      "reviews": 154,
      "discount": "-10%",
      "price": "$89.98",
      "extracted_price": 89.98,
      "old_price": "$99.99",
      "extracted_old_price": 99.99,
      "prime": true
    },
    {
      "position": 7,
      "asin": "B0GF8WCB18",
      "title": "Portable Collapsible Dog Crate for Large Dogs, 4 Mesh Doors & 2 Storage Bags, Indoo...",
      "link": "https://www.amazon.com/sspa/click?ie=UTF8&spc=MTo2NzE0MjY4MzIxMDk0MTM5OjE3NzU5ODEwNDM6c3BfZGV0YWlsOjMwMTE5NTIxNjc0NzgwMjo6Ojo&url=%2Fdp%2FB0GF8WCB18%2Fref%3Dsspa_dk_detail_6%3Fpsc%3D1%26pd_rd_i%3DB0GF8WCB18%26pd_rd_w%3D1N3gE%26content-id%3Damzn1.sym.613a5a0c-ad86-44dc-b9ed-5da62fb83b9e%26pf_rd_p%3D613a5a0c-ad86-44dc-b9ed-5da62fb83b9e%26pf_rd_r%3D7G2FD7MKN8KHFEPRZ04K%26pd_rd_wg%3DKY4uL%26pd_rd_r%3Dab42157f-1806-47ab-81af-017f1ceb4f98%26sp_csd%3Dd2lkZ2V0TmFtZT1zcF9kZXRhaWw",
      "link_clean": "https://www.amazon.com/dp/B0GF8WCB18/",
      "serpapi_link": "https://serpapi.com/search.json?amazon_domain=amazon.com&asin=B0GF8WCB18&device=desktop&engine=amazon_product",
      "sponsored": true,
      "thumbnail": "https://m.media-amazon.com/images/I/81vBDXjxzsL._AC_UF480,480_SR480,480_.jpg",
      "rating": 4.9,
      "reviews": 27,
      "price": "$89.99",
      "extracted_price": 89.99,
      "prime": true
    },
    {
      "position": 8,
      "asin": "B0FDPVJH5Q",
      "title": "ZOMISIA Collapsible Dog Crate for Dogs - 28\" L Heavy Duty Dog Kennel No Tools Required with 4 Sides Steel Foldable Cage for Dogs Indoor Furniture, Portable Carrier with 2 Smooth Wheels, Beige",
      "link": "https://www.amazon.com/sspa/click?ie=UTF8&spc=MTo2NDY2ODMyMDMzNzU2Njg6MTc3NTk4MTA0MzpzcF9kZXRhaWwyOjMwMTIyMDMwMzM4ODMwMjo6Ojo&url=%2Fdp%2FB0FDPVJH5Q%2Fref%3Dsspa_dk_detail_0%3Fpsc%3D1%26pd_rd_i%3DB0FDPVJH5Q%26pd_rd_w%3DPo4NF%26content-id%3Damzn1.sym.953c7d66-4120-4d22-a777-f19dbfa69309%26pf_rd_p%3D953c7d66-4120-4d22-a777-f19dbfa69309%26pf_rd_r%3D7G2FD7MKN8KHFEPRZ04K%26pd_rd_wg%3DKY4uL%26pd_rd_r%3Dab42157f-1806-47ab-81af-017f1ceb4f98%26sp_csd%3Dd2lkZ2V0TmFtZT1zcF9kZXRhaWwy",
      "link_clean": "https://www.amazon.com/dp/B0FDPVJH5Q/",
      "serpapi_link": "https://serpapi.com/search.json?amazon_domain=amazon.com&asin=B0FDPVJH5Q&device=desktop&engine=amazon_product",
      "sponsored": true,
      "badges": [
        "Limited time deal"
      ],
      "thumbnail": "https://m.media-amazon.com/images/I/81YdRCpJqKL._AC_UF480,480_SR480,480_.jpg",
      "rating": 4.6,
      "reviews": 154,
      "discount": "-10%",
      "price": "$89.98",
      "extracted_price": 89.98,
      "old_price": "$99.99",
      "extracted_old_price": 99.99,
      "prime": true
    },
    {
      "position": 9,
      "asin": "B09D8KSWTV",
      "title": "KindTail PAWD Collapsible Puppy and Dog Crate + Washable Bed - Stylish Pet Kennel with Comfortable Pad - Safe Indoor Set - Lightweight, Compact & Portable for Travel - Small White",
      "link": "https://www.amazon.com/sspa/click?ie=UTF8&spc=MTo2NDY2ODMyMDMzNzU2Njg6MTc3NTk4MTA0MzpzcF9kZXRhaWwyOjMwMTIzNDk3MTg3MjAwMjo6Ojo&url=%2Fdp%2FB09D8KSWTV%2Fref%3Dsspa_dk_detail_1%3Fpsc%3D1%26pd_rd_i%3DB09D8KSWTV%26pd_rd_w%3DPo4NF%26content-id%3Damzn1.sym.953c7d66-4120-4d22-a777-f19dbfa69309%26pf_rd_p%3D953c7d66-4120-4d22-a777-f19dbfa69309%26pf_rd_r%3D7G2FD7MKN8KHFEPRZ04K%26pd_rd_wg%3DKY4uL%26pd_rd_r%3Dab42157f-1806-47ab-81af-017f1ceb4f98%26sp_csd%3Dd2lkZ2V0TmFtZT1zcF9kZXRhaWwy",
      "link_clean": "https://www.amazon.com/dp/B09D8KSWTV/",
      "serpapi_link": "https://serpapi.com/search.json?amazon_domain=amazon.com&asin=B09D8KSWTV&device=desktop&engine=amazon_product",
      "sponsored": true,
      "badges": [
        "Amazon's Choice"
      ],
      "thumbnail": "https://m.media-amazon.com/images/I/61jTpS6FsTL._AC_UF480,480_SR480,480_.jpg",
      "rating": 4.1,
      "reviews": 69,
      "price": "$129.99",
      "extracted_price": 129.99,
      "price_unit": "$129.99 / count",
      "extracted_price_unit": 129.99,
      "prime": true
    },
    {
      "position": 10,
      "asin": "B0G5X32CW4",
      "title": "Hard Cat Carrier,Dog Crate for Small Dogs,Cat Kennel Clear,Foldable Dog Kennel with...",
      "link": "https://www.amazon.com/sspa/click?ie=UTF8&spc=MTo2NDY2ODMyMDMzNzU2Njg6MTc3NTk4MTA0MzpzcF9kZXRhaWwyOjMwMTE2MjEyNDk3MDYwMjo6Ojo&url=%2Fdp%2FB0G5X32CW4%2Fref%3Dsspa_dk_detail_2%3Fpsc%3D1%26pd_rd_i%3DB0G5X32CW4%26pd_rd_w%3DPo4NF%26content-id%3Damzn1.sym.953c7d66-4120-4d22-a777-f19dbfa69309%26pf_rd_p%3D953c7d66-4120-4d22-a777-f19dbfa69309%26pf_rd_r%3D7G2FD7MKN8KHFEPRZ04K%26pd_rd_wg%3DKY4uL%26pd_rd_r%3Dab42157f-1806-47ab-81af-017f1ceb4f98%26sp_csd%3Dd2lkZ2V0TmFtZT1zcF9kZXRhaWwy",
      "link_clean": "https://www.amazon.com/dp/B0G5X32CW4/",
      "serpapi_link": "https://serpapi.com/search.json?amazon_domain=amazon.com&asin=B0G5X32CW4&device=desktop&engine=amazon_product",
      "sponsored": true,
      "thumbnail": "https://m.media-amazon.com/images/I/61SZBa3ZrdL._AC_UF480,480_SR480,480_.jpg",
      "rating": 3.9,
      "reviews": 9,
      "price": "$59.99",
      "extracted_price": 59.99,
      "prime": true
    },
    {
      "position": 11,
      "asin": "B0GF8WCB18",
      "title": "Portable Collapsible Dog Crate for Large Dogs, 4 Mesh Doors & 2 Storage Bags, Indoo...",
      "link": "https://www.amazon.com/sspa/click?ie=UTF8&spc=MTo2NDY2ODMyMDMzNzU2Njg6MTc3NTk4MTA0MzpzcF9kZXRhaWwyOjMwMTE5NTIxNjc0NzgwMjo6Ojo&url=%2Fdp%2FB0GF8WCB18%2Fref%3Dsspa_dk_detail_3%3Fpsc%3D1%26pd_rd_i%3DB0GF8WCB18%26pd_rd_w%3DPo4NF%26content-id%3Damzn1.sym.953c7d66-4120-4d22-a777-f19dbfa69309%26pf_rd_p%3D953c7d66-4120-4d22-a777-f19dbfa69309%26pf_rd_r%3D7G2FD7MKN8KHFEPRZ04K%26pd_rd_wg%3DKY4uL%26pd_rd_r%3Dab42157f-1806-47ab-81af-017f1ceb4f98%26sp_csd%3Dd2lkZ2V0TmFtZT1zcF9kZXRhaWwy",
      "link_clean": "https://www.amazon.com/dp/B0GF8WCB18/",
      "serpapi_link": "https://serpapi.com/search.json?amazon_domain=amazon.com&asin=B0GF8WCB18&device=desktop&engine=amazon_product",
      "sponsored": true,
      "thumbnail": "https://m.media-amazon.com/images/I/81vBDXjxzsL._AC_UF480,480_SR480,480_.jpg",
      "rating": 4.9,
      "reviews": 27,
      "price": "$89.99",
      "extracted_price": 89.99,
      "prime": true
    },
    {
      "position": 12,
      "asin": "B07GKYW3KR",
      "title": "SportPet Airline Compliant MEDIUM 24.25\" Travel Dog Kennel-Durable Plastic Airline Pet Carrier w/Removable Wheels & Food Bowls, Collapsible Indoor/Outdoor Dog Kennel, Dogs up to 23\"L & 15\"H-Cream/Gray",
      "link": "https://www.amazon.com/sspa/click?ie=UTF8&spc=MTo2NDY2ODMyMDMzNzU2Njg6MTc3NTk4MTA0MzpzcF9kZXRhaWwyOjMwMTIxODQ1NTgzNDQwMjo6Ojo&url=%2Fdp%2FB07GKYW3KR%2Fref%3Dsspa_dk_detail_4%3Fpsc%3D1%26pd_rd_i%3DB07GKYW3KR%26pd_rd_w%3DPo4NF%26content-id%3Damzn1.sym.953c7d66-4120-4d22-a777-f19dbfa69309%26pf_rd_p%3D953c7d66-4120-4d22-a777-f19dbfa69309%26pf_rd_r%3D7G2FD7MKN8KHFEPRZ04K%26pd_rd_wg%3DKY4uL%26pd_rd_r%3Dab42157f-1806-47ab-81af-017f1ceb4f98%26sp_csd%3Dd2lkZ2V0TmFtZT1zcF9kZXRhaWwy",
      "link_clean": "https://www.amazon.com/dp/B07GKYW3KR/",
      "serpapi_link": "https://serpapi.com/search.json?amazon_domain=amazon.com&asin=B07GKYW3KR&device=desktop&engine=amazon_product",
      "sponsored": true,
      "thumbnail": "https://m.media-amazon.com/images/I/71BtFj+Mi9L._AC_UF480,480_SR480,480_.jpg",
      "rating": 4.5,
      "reviews": 6147,
      "discount": "-13%",
      "price": "$79.99",
      "extracted_price": 79.99,
      "old_price": "$92.00",
      "extracted_old_price": 92,
      "prime": true
    },
    {
      "position": 13,
      "asin": "B0D83PD1DL",
      "title": "Veraste 42\" L x 31\" W x 31\" H Collapsible Travel Dog Crate, Quick-Setup Portable Soft Dog Kennel for Large Dogs up to 90 lbs, 4-Door Foldable Travel Crate with Storage Bag, Black",
      "link": "https://www.amazon.com/sspa/click?ie=UTF8&spc=MTo2NDY2ODMyMDMzNzU2Njg6MTc3NTk4MTA0MzpzcF9kZXRhaWwyOjMwMDg3NzQ4MTc2NzAwMjo6Ojo&url=%2Fdp%2FB0D83PD1DL%2Fref%3Dsspa_dk_detail_5%3Fpsc%3D1%26pd_rd_i%3DB0D83PD1DL%26pd_rd_w%3DPo4NF%26content-id%3Damzn1.sym.953c7d66-4120-4d22-a777-f19dbfa69309%26pf_rd_p%3D953c7d66-4120-4d22-a777-f19dbfa69309%26pf_rd_r%3D7G2FD7MKN8KHFEPRZ04K%26pd_rd_wg%3DKY4uL%26pd_rd_r%3Dab42157f-1806-47ab-81af-017f1ceb4f98%26sp_csd%3Dd2lkZ2V0TmFtZT1zcF9kZXRhaWwy",
      "link_clean": "https://www.amazon.com/dp/B0D83PD1DL/",
      "serpapi_link": "https://serpapi.com/search.json?amazon_domain=amazon.com&asin=B0D83PD1DL&device=desktop&engine=amazon_product",
      "sponsored": true,
      "thumbnail": "https://m.media-amazon.com/images/I/71J5uIBqVsL._AC_UF480,480_SR480,480_.jpg",
      "rating": 3.8,
      "reviews": 479,
      "price": "$109.99",
      "extracted_price": 109.99,
      "price_unit": "$109.99 / count",
      "extracted_price_unit": 109.99,
      "prime": true
    },
    {
      "position": 14,
      "asin": "B000GF5FKO",
      "title": "NaturVet Quiet Moments Herbal Calming Room Spray Dog Supplement - Ideal for Cars, Dog Crates, New Environments - Helps Reduce Pet Stress, Storm Anxiety, Motion Sickness - 8 Oz.",
      "link": "https://www.amazon.com/sspa/click?ie=UTF8&spc=MTo2NDY2ODMyMDMzNzU2Njg6MTc3NTk4MTA0MzpzcF9kZXRhaWwyOjMwMTIzNDQ3OTc0MjQwMjo6Ojo&url=%2Fdp%2FB000GF5FKO%2Fref%3Dsspa_dk_detail_6%3Fpsc%3D1%26pd_rd_i%3DB000GF5FKO%26pd_rd_w%3DPo4NF%26content-id%3Damzn1.sym.953c7d66-4120-4d22-a777-f19dbfa69309%26pf_rd_p%3D953c7d66-4120-4d22-a777-f19dbfa69309%26pf_rd_r%3D7G2FD7MKN8KHFEPRZ04K%26pd_rd_wg%3DKY4uL%26pd_rd_r%3Dab42157f-1806-47ab-81af-017f1ceb4f98%26sp_csd%3Dd2lkZ2V0TmFtZT1zcF9kZXRhaWwy%26smid%3DA1CB8NAA00AH8Y",
      "link_clean": "https://www.amazon.com/dp/B000GF5FKO/",
      "serpapi_link": "https://serpapi.com/search.json?amazon_domain=amazon.com&asin=B000GF5FKO&device=desktop&engine=amazon_product",
      "sponsored": true,
      "thumbnail": "https://m.media-amazon.com/images/I/61BOnhJESML._AC_UF480,480_SR480,480_.jpg",
      "rating": 4,
      "reviews": 2912,
      "discount": "-17%",
      "price": "$14.97",
      "extracted_price": 14.97,
      "old_price": "$17.96",
      "extracted_old_price": 17.96,
      "save_with_coupon": "Save $3.00",
      "prime": true
    }
  ],
  "sustainability_features": {
    "summary": "This product has sustainability features recognized by trusted certifications.",
    "climate_pledge_friendly": true,
    "learn_more_link": "https://www.amazon.com/climatepledgefriendly",
    "features": [
      {
        "position": 1,
        "title": "Recycled materials",
        "text": "Contains at least 50% recycled material.",
        "certified_by": [
          {
            "name": "Global Recycled Standard",
            "logo": "https://m.media-amazon.com/images/I/51IhSrucIyL._SS144_.png",
            "description": "Global Recycled Standard (GRS) certified products contain recycled content that has been independently verified at each stage of the supply chain, from the source to the final product and meet social, environmental, and chemical requirements. The purchase of Global Recycled Standard (GRS) certified products supports the use of recycled content in the supply chain. A product must contain at least 50% certified GRS material to qualify for inclusion in Climate Pledge Friendly.",
            "link": "https://textileexchange.org/integrity/"
          }
        ]
      },
      {
        "position": 2,
        "title": "Safer chemicals",
        "text": "Made with chemicals safer for human health and the environment.",
        "certified_by": [
          {
            "name": "Global Recycled Standard",
            "logo": "https://m.media-amazon.com/images/I/51IhSrucIyL._SS144_.png",
            "description": "Global Recycled Standard (GRS) certified products contain recycled content that has been independently verified at each stage of the supply chain, from the source to the final product and meet social, environmental, and chemical requirements. The purchase of Global Recycled Standard (GRS) certified products supports the use of recycled content in the supply chain. A product must contain at least 50% certified GRS material to qualify for inclusion in Climate Pledge Friendly.",
            "link": "https://textileexchange.org/integrity/"
          }
        ]
      },
      {
        "position": 3,
        "title": "Worker well-being",
        "text": "Manufactured on farms or in facilities that protect the rights and/or health of workers.",
        "certified_by": [
          {
            "name": "Global Recycled Standard",
            "logo": "https://m.media-amazon.com/images/I/51IhSrucIyL._SS144_.png",
            "description": "Global Recycled Standard (GRS) certified products contain recycled content that has been independently verified at each stage of the supply chain, from the source to the final product and meet social, environmental, and chemical requirements. The purchase of Global Recycled Standard (GRS) certified products supports the use of recycled content in the supply chain. A product must contain at least 50% certified GRS material to qualify for inclusion in Climate Pledge Friendly.",
            "link": "https://textileexchange.org/integrity/"
          }
        ]
      }
    ]
  },
  "videos": [
    {
      "position": 1,
      "title": "Collapsible Dog Crate with Wheels - Easy to Store Perfect for Travel",
      "link": "https://m.media-amazon.com/images/S/vse-vms-transcoding-artifact-us-east-1-prod/222ee7f0-60d9-46fc-acec-ab2d59210ecd/default.jobtemplate.hls.m3u8",
      "thumbnail": "https://m.media-amazon.com/images/I/61BKBDm7RUL.jpg",
      "duration": "3:49",
      "vendor": "Jennifer Tarle - Favorites & Fun",
      "vendor_thumbnail": "https://m.media-amazon.com/images/I/815QsrnsOzL._CR0,0,2153,2153_._FMjpg_._SL34_.jpg",
      "date": "Jan 19, 2026"
    },
    {
      "position": 2,
      "title": "Collapsible Dog Crate",
      "link": "https://m.media-amazon.com/images/S/vse-vms-transcoding-artifact-us-east-1-prod/684f0a47-168d-4826-aa52-3eb7c31fc5ca/default.jobtemplate.hls.m3u8",
      "thumbnail": "https://m.media-amazon.com/images/I/51fi0CQ1j+L.jpg",
      "duration": "0:35",
      "vendor": "Gardner Pet Official",
      "date": "Dec 31, 2025"
    },
    {
      "position": 3,
      "title": "Watch This Foldable (and FASHION) Dog Crate",
      "link": "https://m.media-amazon.com/images/S/vse-vms-transcoding-artifact-us-east-1-prod/718d9b15-2685-4080-ad8a-85f40d4f499e/default.jobtemplate.hls.m3u8",
      "thumbnail": "https://m.media-amazon.com/images/I/A1O00vFUaJL.png",
      "duration": "1:04",
      "vendor": "May Gonzalez",
      "vendor_thumbnail": "https://m.media-amazon.com/images/I/A1psq8QBr1L._CR0,0,1738,1738_._FMjpg_._SL34_.jpg",
      "date": "Jan 19, 2026"
    },
    {
      "position": 4,
      "title": "Travel Kennel / Dog Crate Unboxing &amp; Review",
      "link": "https://m.media-amazon.com/images/S/vse-vms-transcoding-artifact-us-east-1-prod/538e9996-f155-4f05-9df3-8c3c1c074863/default.jobtemplate.hls.m3u8",
      "thumbnail": "https://m.media-amazon.com/images/I/91A8msHNEuL.jpg",
      "duration": "7:11",
      "vendor": "Murphy McCammon",
      "vendor_thumbnail": "https://m.media-amazon.com/images/I/9109RlAgsLL._CR0,0,1024,1024_._FMjpg_._SL34_.jpg",
      "date": "Jan 16, 2026"
    },
    {
      "position": 5,
      "title": "My Honest Review On The Travel Dog Crate With Wheels",
      "link": "https://m.media-amazon.com/images/S/vse-vms-transcoding-artifact-us-east-1-prod/793befc4-dae1-40eb-981c-1d3845e35a52/default.jobtemplate.hls.m3u8",
      "thumbnail": "https://m.media-amazon.com/images/I/B15fJwXQ8IL.png",
      "duration": "1:08",
      "vendor": "abi reviews",
      "vendor_thumbnail": "https://m.media-amazon.com/images/I/B1IeuQRVqVL._CR5,50,2302,2301_._FMjpg_._SL34_.jpg",
      "date": "Jan 16, 2026"
    },
    {
      "position": 6,
      "title": "Good Looking High Quality Crate - Easy Fold & Very Sturdy!",
      "link": "https://m.media-amazon.com/images/S/vse-vms-transcoding-artifact-us-east-1-prod/09db5ef2-52d2-443e-8b63-90faeafadccb/default.jobtemplate.hls.m3u8",
      "thumbnail": "https://m.media-amazon.com/images/I/61UNfWbeJeL.jpg",
      "duration": "1:05",
      "vendor": "Vivi Lareau",
      "vendor_thumbnail": "https://m.media-amazon.com/images/S/amazon-avatars-global/ddeb6018-e66d-4f27-932f-cdfcebda104b._CR0%2C0%2C456%2C456_UX460_._SL34_.jpg",
      "date": "Jan 12, 2026"
    },
    {
      "position": 7,
      "title": "How To Use Collapsible Dog Crate",
      "link": "https://m.media-amazon.com/images/S/vse-vms-transcoding-artifact-us-east-1-prod/ec00411e-cc2f-45e5-99e8-2857c4e03f21/default.jobtemplate.hls.m3u8",
      "thumbnail": "https://m.media-amazon.com/images/I/51lQ4JMkMdL.jpg",
      "duration": "0:24",
      "vendor": "Gardner Pet Official",
      "date": "Dec 31, 2025"
    },
    {
      "position": 8,
      "title": "So Great! Opens and Closes in a Snap!!!",
      "link": "https://m.media-amazon.com/images/S/vse-vms-transcoding-artifact-us-east-1-prod/4d662aa5-4927-4388-9796-750a2c4cc766/default.vertical.jobtemplate.hls.m3u8",
      "thumbnail": "https://m.media-amazon.com/images/I/61CcHfy4srL.jpg",
      "duration": "0:32",
      "vendor": "Unbiased Reviews",
      "vendor_thumbnail": "https://m.media-amazon.com/images/S/amazon-avatars-global/default._SL34_.png",
      "date": "Jan 16, 2026"
    },
    {
      "position": 9,
      "title": "Sturdy and comfortable travel crate",
      "link": "https://m.media-amazon.com/images/S/vse-vms-transcoding-artifact-us-east-1-prod/f7a5f321-8846-4c6e-80e6-16a7de84b5b2/default.vertical.jobtemplate.hls.m3u8",
      "thumbnail": "https://m.media-amazon.com/images/I/51y-r4IddEL.jpg",
      "duration": "0:44",
      "vendor": "ChihuahuaLover",
      "vendor_thumbnail": "https://m.media-amazon.com/images/S/amazon-avatars-global/default._SL34_.png",
      "date": "Jan 21, 2026"
    }
  ],
  "product_description": [
    {
      "position": 1,
      "title": "dog crate",
      "image": "https://m.media-amazon.com/images/S/aplus-media-library-service-media/eb946d97-f6e0-4bf1-987d-64e30f6545d4.__CR0,0,1464,600_PT0_SX1464_V1___.jpg"
    },
    {
      "position": 2,
      "carousel_images": [
        {
          "position": 1,
          "title": "large dog crate",
          "image": "https://m.media-amazon.com/images/S/aplus-media-library-service-media/17e033d0-79c9-4d2e-938c-5d91fb5190a0.__CR0,0,1464,600_PT0_SX1464_V1___.jpg"
        },
        {
          "position": 2,
          "title": "dog kennel",
          "image": "https://m.media-amazon.com/images/S/aplus-media-library-service-media/012d1a8f-b43f-405b-b9eb-deb06706b87f.__CR0,0,1464,600_PT0_SX1464_V1___.jpg"
        }
      ]
    },
    {
      "position": 3
    },
    {
      "position": 4,
      "carousel_images": [
        {
          "position": 1,
          "title": "Collapsible Dog Crate",
          "image": "https://m.media-amazon.com/images/S/aplus-media-library-service-media/c66102dc-3692-492e-8f13-478d3126457f.__CR0,0,1464,600_PT0_SX1464_V1___.png"
        },
        {
          "position": 2,
          "title": "Gardner Pet Dog Crate",
          "image": "https://m.media-amazon.com/images/S/aplus-media-library-service-media/6c3e8d01-7b06-4f7b-9ba5-0534e1ad9a82.__CR0,0,1464,600_PT0_SX1464_V1___.png"
        }
      ]
    },
    {
      "position": 5,
      "title": "dog cage",
      "image": "https://m.media-amazon.com/images/S/aplus-media-library-service-media/9748b623-5136-464e-8dfe-3f0508915998.__CR0,0,1464,600_PT0_SX1464_V1___.png"
    },
    {
      "position": 6,
      "compare_with_similar": [
        {
          "position": 1,
          "asin": "B0FPF8VSY9",
          "title": "Collapsible Dog Crate",
          "thumbnail": "https://m.media-amazon.com/images/S/aplus-media-library-service-media/655901b6-7d90-489a-8ba5-b8a0117d9009.__AC_SR200,225___.jpg",
          "link": "https://www.amazon.com/dp/B0FPF8VSY9?ref=emc_p_m_5_i_atc",
          "serpapi_link": "https://serpapi.com/search.json?amazon_domain=amazon.com&asin=B0FPF8VSY9&device=desktop&engine=amazon_product",
          "rating": 4.9,
          "reviews": 48,
          "price": "$149.99",
          "extracted_price": 149.99,
          "material": "PP",
          "size_available": "28 inch/36 inch",
          "color_available": "White",
          "occasion": "Indoor & Outdoor",
          "feature": "Space-Saving & Easy Mobility"
        },
        {
          "position": 2,
          "asin": "B0FJXWPGF8",
          "title": "Diamond Mesh Dog Kennel",
          "thumbnail": "https://m.media-amazon.com/images/S/aplus-media-library-service-media/cbf0d8ec-ca94-4547-92b7-499388c6d115.__AC_SR200,225___.jpg",
          "link": "https://www.amazon.com/dp/B0FJXWPGF8?ref=emc_p_m_5_i_atc",
          "serpapi_link": "https://serpapi.com/search.json?amazon_domain=amazon.com&asin=B0FJXWPGF8&device=desktop&engine=amazon_product",
          "rating": 4,
          "reviews": 33,
          "price": "$104.39",
          "extracted_price": 104.39,
          "material": "Metal&PP",
          "size_available": "30 inch/36 inch/42 inch",
          "color_available": "White",
          "occasion": "Indoor",
          "feature": "Instant Foldable&Space-Saving"
        },
        {
          "position": 3,
          "asin": "B0DSLH9JCN",
          "title": "Soft Collapsible Crate",
          "thumbnail": "https://m.media-amazon.com/images/S/aplus-media-library-service-media/16d48379-ba72-4de2-8185-4d58b2a282e7.__AC_SR200,225___.jpg",
          "link": "https://www.amazon.com/dp/B0DSLH9JCN?ref=emc_p_m_5_i_atc",
          "serpapi_link": "https://serpapi.com/search.json?amazon_domain=amazon.com&asin=B0DSLH9JCN&device=desktop&engine=amazon_product",
          "rating": 4.3,
          "reviews": 139,
          "price": "$84.99",
          "extracted_price": 84.99,
          "material": "Nylon&Metal",
          "size_available": "26 inch/30 inch/36 inch",
          "color_available": "Blue/Green",
          "occasion": "Indoor & Outdoor",
          "feature": "Travel-Optimized-portable bag"
        },
        {
          "position": 4,
          "asin": "B0FK4GWN33",
          "title": "Duty Dog Crate Furniture",
          "thumbnail": "https://m.media-amazon.com/images/S/aplus-media-library-service-media/d6999f22-52a2-4f02-a1f1-95d59a7f61e6.__AC_SR200,225___.jpg",
          "link": "https://www.amazon.com/dp/B0FK4GWN33?ref=emc_p_m_5_i_atc",
          "serpapi_link": "https://serpapi.com/search.json?amazon_domain=amazon.com&asin=B0FK4GWN33&device=desktop&engine=amazon_product",
          "rating": 4.4,
          "reviews": 104,
          "price": "$129.99",
          "extracted_price": 129.99,
          "material": "Engineered Wood&Metal",
          "size_available": "27 inch/32 inch/38 inch",
          "color_available": "Rustic Brown/Rustic Grey",
          "occasion": "Indoor",
          "feature": "Integration with Home Decor"
        },
        {
          "position": 5,
          "asin": "B0GH86BB11",
          "title": "Heavy Duty Dog Crate",
          "thumbnail": "https://m.media-amazon.com/images/S/aplus-media-library-service-media/85689d2b-d3e4-49d7-b432-95616c121d16.__AC_SR200,225___.jpg",
          "link": "https://www.amazon.com/dp/B0GH86BB11?ref=emc_p_m_5_i_atc",
          "serpapi_link": "https://serpapi.com/search.json?amazon_domain=amazon.com&asin=B0GH86BB11&device=desktop&engine=amazon_product",
          "rating": 4.8,
          "reviews": 8,
          "price": "$139.99",
          "extracted_price": 139.99,
          "material": "Metal",
          "size_available": "32 inch/43 inch",
          "color_available": "Black/Brown",
          "occasion": "Indoor",
          "feature": "Triple-Door Lock Design"
        },
        {
          "position": 6,
          "asin": "B0F999QPXL",
          "title": "Decorative Garden Fence",
          "thumbnail": "https://m.media-amazon.com/images/S/aplus-media-library-service-media/76e3f7ca-96cb-4554-8ec2-d117ba7e98c7.__AC_SR200,225___.jpg",
          "link": "https://www.amazon.com/dp/B0F999QPXL?ref=emc_p_m_5_i_atc",
          "serpapi_link": "https://serpapi.com/search.json?amazon_domain=amazon.com&asin=B0F999QPXL&device=desktop&engine=amazon_product",
          "rating": 4.7,
          "reviews": 63,
          "price": "$159.99",
          "extracted_price": 159.99,
          "material": "Metal",
          "size_available": "24 inch/32 inch/40 inch",
          "color_available": "Black/Brown",
          "occasion": "Indoor & Outdoor",
          "feature": "Gravity-Locked Gate"
        },
        {
          "position": 7,
          "asin": "B0D9XTB69K",
          "title": "Dog Playpens",
          "thumbnail": "https://m.media-amazon.com/images/S/aplus-media-library-service-media/1b86d933-d98e-48d6-a512-2806a59ef1e6.__AC_SR200,225___.jpg",
          "link": "https://www.amazon.com/dp/B0D9XTB69K?ref=emc_p_m_5_i_atc",
          "serpapi_link": "https://serpapi.com/search.json?amazon_domain=amazon.com&asin=B0D9XTB69K&device=desktop&engine=amazon_product",
          "rating": 4.6,
          "reviews": 239,
          "price": "$49.99",
          "extracted_price": 49.99,
          "material": "Metal",
          "size_available": "24 inch/32 inch/40 inch",
          "color_available": "Black/Brown",
          "occasion": "Indoor & Outdoor",
          "feature": "Gravity-Locked Gate"
        }
      ]
    }
  ],
  "product_details": {
    "brand_name": "Gardner Pet",
    "target_species": "Dog",
    "specific_uses_for_product": "Indoor, Outdoor",
    "breed_recommendation": "Small",
    "dog_breed_size": "Medium, Small",
    "manufacturer": "Gardner Pet",
    "unit_count": "1.0 Count",
    "best_sellers_rank": [
      {
        "text": "#11,344 in Pet Supplies (See Top 100 in Pet Supplies)",
        "extracted_rank": 11344,
        "link": "https://www.amazon.com/gp/bestsellers/pet-supplies/ref=pd_zg_ts_pet-supplies",
        "link_text": "See Top 100 in Pet Supplies"
      },
      {
        "text": "#8 in Dog Hard-Sided Carriers",
        "extracted_rank": 8,
        "link": "https://www.amazon.com/gp/bestsellers/pet-supplies/3024187011/ref=pd_zg_hrsr_pet-supplies",
        "link_text": "Dog Hard-Sided Carriers"
      }
    ],
    "asin": "B0FPF6VZJ7",
    "rating": 4.9,
    "reviews": 48,
    "additional_features": "Collapsible, Easy to Use, Hard Case, Heavy Duty, Portable",
    "number_of_levels": "1",
    "material_type": "50% Recycled pre-consumer Metal (RM0248) + 48%Polypropylene (RM0202) +2% Polyethylene terephthalate (PET) (RM0194)\"",
    "color": "Grey",
    "item_dimensions_l_x_w_x_h": "27.96\"L x 18.3\"W x 20.87\"H",
    "item_weight": "8.19 Kilograms",
    "product_dimensions": "27.96 x 18.3 x 20.87 inches; 18.05 Pounds",
    "item_model_number": "GP01I6525GY",
    "date_first_available": "January 1, 2026"
  },
  "sponsored_brands": [
    {
      "position": 1,
      "asin": "B09TFFZR66",
      "title": "Prutapet Large Cat Carrier 24\"x16.5\"x16.5\" Portable Dog Crate for Small Medium Dogs Collapsible Traveling Pet Crate with Collapsible Bowl",
      "link": "https://aax-us-east-retail-direct.amazon.com/x/c/JByPwLLvj71VZa7yWqnAeFUAAAGdgLgfpQEAAAH2AQBvbm9fdHhuX2JpZDUgICBvbm9fdHhuX2ltcDIgICBJxzbS/clv1c_ek-wBXfWbcbSXg5XY7vi_kTD8ESxt6CZ35KMwBNoyRMsrDsuZSGKDnCxU7gg-VT66dufiYMRNCpG2K-mLadznAupQ2oJWol-K3vO9cCkiWQcAZfVEQZ_Hcz76N8gzjGb4J1NX8TWT76QGOcmZNBJedLj8F2dnVHpgPzoD5epTgAZVFJ4iPITiwr1fQHGYjrQxgy8ZEVFGVNQ8PDdZgSJoA6LTA4qBp_UXrj6QrENn1K-3TJv5mZcnNRkUH5eeVkZjmS_xvR_Yu7D3LzDCtX6sA1nA8p8KlEG22uOgkJDC6_-iLYgv8hqDOoPeoVca0n5O5OHoaSFRWXqxfIqpTGEWSw5hi6QcQln4VMZ0e4KwuOxFeio2QjCqO0SuKFvMUEXDY9HoKI3ODV4Ngv_9Z0DUZjs17B3otI0K_VKdvgCsLxGbGBAVuBhepnOR8GeFI7oIP3gtlyFJUahiyF3NaGmHQLIih4lLT-aYvXVonGZFUXU8581gwSYjuZYKPML21Po4jBb69u4JQ5VXWDp0u1gvkgIFCW6xnkcKNcaSFa4JlZt96us3B5uZL4piqN3kOyNfXFa1PNRsGVyJHx8-2qvbS84UWGPfyexHECn26Lvfqsv06tQcsfuzR-IaO3mh_8Y_DRAcETuwUIzivDKGE85cYYz9GP4S9YSGcv6NhlMBpYoS6ljtTlBXY_5VZytQC1zpUaiRK3ql4vDX85piMqy5JKGn_fo2dUfoZ3J2gjyYcP_X-7fmO8w0zby8MXLU-rdTxq81HP8azvIM7uol8eaqIgFjPeOpgc2kSFoaFg_OLrxl5wyV2ssONLY9C50DFqYJnXq2jDF06xAna_001JG-DSQpZDX5z6SnmfQDxin6s2jxkXv9AMLpWVo9pfuMt3Pp5PVU4K8KV1vMiT0wEylFQeBTKDJnfR2Z4gS9fUIMEuhrbzldPSJn4y-2riSmMT_pv30IHz4xlf1wfyg0jkE5qiHuuhT61FZsjE0LfXZODFCd84NcONi-VZn6Dk-NSZfhDCLSSIWqimSRc-24wbtHl8aXiWhtXej8qLJUWgCzOd8vlA4UDlv3p2HXTFmdsnp0sgAOigg6Sjz9137FTN2v8rE9IHiPI8CwsIbJaNZESxhC8-ZfIPzEwoZMwXmt5Vs4FMO0eNIpIWHsIAIDfRlX8aD4DsTImMf5IYbDiY5KfFQlG_rjqDntPybeGysXO5m2vCMulQAJ18jphuzTPvka6QeSYDHvpq2FEBNyFikFxoBL2dHx3ceKsB0W8RNKbE7y7oyG09hpvC_ZBezGU_yfHem3yHgAlOb7f_QXbze9mwd235h_S-z-2gmrqz7v1sdsJJPWiD5zv-ptB6XC0gtqF8WhvBVOjhqthcRBHGmT67L5Dq7OxbI5ksyshZrKYP5VMhaiL0IADW1HycdECxkCieFOR41CipD0NKn0id61blRbTD8vnJlPYOU_gIwHEmleuD_wflNvMsf0o-5qvDnMc0_JTFxl9FB1QWep284cP8VOPJilTfnxk3nWM5FF6y3sQ37ZgjBDgth-fMLvPr8nw/https://www.amazon.com/dp/B09TFFZR66/?_encoding=UTF8&pd_rd_i=B09TFFZR66&pd_rd_i=B09TFFZR66&ref_=sbx_be_s_sparkle_ssd_cta&pd_rd_w=ypYD1&content-id=amzn1.sym.ccb770a9-35d1-4af6-8af2-bcbd12656fbb&pf_rd_p=ccb770a9-35d1-4af6-8af2-bcbd12656fbb&pf_rd_r=7G2FD7MKN8KHFEPRZ04K&pd_rd_wg=KY4uL&pd_rd_r=ab42157f-1806-47ab-81af-017f1ceb4f98",
      "link_clean": "https://www.amazon.com/dp/B09TFFZR66/",
      "serpapi_link": "https://serpapi.com/search.json?amazon_domain=amazon.com&asin=B09TFFZR66&device=desktop&engine=amazon_product",
      "thumbnail": "https://m.media-amazon.com/images/I/416ACT5uqlL._AC_SR100,100_QL65_.jpg",
      "video": {
        "link": "https://m.media-amazon.com/images/S/al-na-9d5791cf-3faf/19cad161-348c-413d-a15f-903bbd4a4630.mp4/productVideoOptimized.mp4",
        "thumbnail": "https://m.media-amazon.com/images/S/al-na-9d5791cf-3faf/19cad161-348c-413d-a15f-903bbd4a4630.mp4/r/THUMBNAIL_360P_FRAME_3_CAPTURE_2.JPG"
      },
      "rating": 4.8,
      "reviews": 610,
      "price": "$59.99",
      "extracted_price": 59.99,
      "old_price": "$72.99",
      "extracted_old_price": 72.99
    },
    {
      "position": 2,
      "asin": "B0FNDCR59X",
      "title": "46\" Dog Crate Furniture with Wheels, XXL Heavy Duty Dog Kennel Indoor for XL Dogs, Metal Chew-Proof Dog Cage, 45.9\" L x 27.6\" W x 32.4\" H, Decorate House as TV Stand, End Table — Natural and White",
      "link": "https://aax-us-east-retail-direct.amazon.com/x/c/JAmmHaAnTuPEIvVT-sditLEAAAGdgLgfpgEAAAH2AQBvbm9fdHhuX2JpZDUgICBvbm9fdHhuX2ltcDIgICCXRrTK/clv1c_ek-YBfHXbcbWXixXZLvu-lwLsHSxs2D5xzWpThBovQcQrTa2jzUa__2f2T5_pDm4h0OKU7uHb3Ke_5TYLObfOESeGs0kt-YKyZF3rKfXGsQVLxv2V92dsEy64eUYjiK2jwcBkmfjeIRCqRP1KBRB3FDdtO3cllregcHMw9d6zQURRAFzx1M1gfgrgxCb5Z9Ni2DN7OvKmAbNs-Xk_6BG2qCJ1feXNs-ORapV6Yi7CvKtMnPvQsEUZVs3e4RF7034Q2xPc9sWqEpaGkTO8xf1LZAOeDpsls5PiJk26JD9MVrVKpPxmPDm3VlQ2qGH6lW9wrF5jpNSLPgJQoOSXGJ-E0NZB2UATc96MlakEPdwWzpuFHGhhR_8j91sgKIz3jIHS0OUHHAWhQSjKUUbFrC1VBYRrZGaScotcWM2OvYZIqVvizLzr_MThZEAo6x-3C9BU7IlAohl6IQWqeqrBxvKLOCBQEjZiqbYGhRnUqVsKq79HF2jo7sWBimPb88jqDtWbhx2NNuNzmuMeK5_-J314zNBQx-9JoKch_bWxUTZUqX_l_8IQ0LDhwgfdq0rqOwPYnnYzJNxtOVSLExs_9H-Yr2ATycf_MfKOjvkClxCyaC0aYGxVuRY0rR293xGhpESoyXNaTDRMPCu0wASn37-sZ5ppYYPF9mBOPUmSqWgQ7GTlB166F7PhyWwhsoY1a4yW_-IIl9GYMlX9t5BmzJpB8hehXhBVIL_47ei4jjxJvcx5QMaIrne2iHKLwQiqOhpv63vJvlUVlX71-SsxV1ByVoAuOSwyuOtnssuyuKqnBlLfweQC3BOaL6k2LurUPgKM8KCsV1oDhXx3Ez3WJpSqId8tsKRaHIgEgankEcrAA3eB8Ui2t9P4veijeYy_8i37grUC0MJKtEUC2wP0hFzigqdEEQeFB6214ayQyPQ4N1ODX5xb_fRXZOM_QVbkKgHIdPeRoihPAZLvRoq63h07FEYnkbrVTxyltQw8weyfWGy7ztnDPPbXJ2YKMh4otimwUviurdQj0RNCl3CA5sTfb5hydoEYMv0Hcieb6EMSAnW9YzJ_9tOCTnNcdhY125xJ0bJOtPiDg8VJLz1dmuUfDjNVUaVNKB27i47GSNglF7qKo-ryCrFHM1kF1J1oLJlpak7kp7oH7TS7X_pzQObtN729ZhZw2PnudBmCrxw4jwukmk9J3uIoKD3C_OhzheZp6T8jTciuwTkn1h1Ebl_LCcYHz9oygJAi8UmnXw7pCr9zEjO3Ebr1Wy6msTrFlHwyJcmvg2smu_CTE-qCgDOq1EtulVVi5OPgyNLRBs-m1UV1HeVxf5e8BuxMh3jFsoS9QF7hiDZUEKFogh_6jeVHgMfndMykdhdx7Hr_9Dw9J3NhCFA0dpAq3_ELoTf5olT06X0g8WSYoR9XMnbbRIord_gNp0879tWFrtHfjm3-J6MIzFr9mEdpfPUtLr-Aq0pkDKPvAYuXBKbLyn7v_bTnU-z2ZN1kEHUW4CxRULkYJt1OTKsND1I6tjIv4pkuhg8mI7fAwGV1A/https://www.amazon.com/dp/B0FNDCR59X/?_encoding=UTF8&pd_rd_i=B0FNDCR59X&pd_rd_i=B0FNDCR59X&ref_=sbx_be_s_sparkle_ssd_cta&pd_rd_w=ypYD1&content-id=amzn1.sym.ccb770a9-35d1-4af6-8af2-bcbd12656fbb&pf_rd_p=ccb770a9-35d1-4af6-8af2-bcbd12656fbb&pf_rd_r=7G2FD7MKN8KHFEPRZ04K&pd_rd_wg=KY4uL&pd_rd_r=ab42157f-1806-47ab-81af-017f1ceb4f98",
      "link_clean": "https://www.amazon.com/dp/B0FNDCR59X/",
      "serpapi_link": "https://serpapi.com/search.json?amazon_domain=amazon.com&asin=B0FNDCR59X&device=desktop&engine=amazon_product",
      "thumbnail": "https://m.media-amazon.com/images/I/41FkY3jshZL._AC_SR100,100_QL65_.jpg",
      "video": {
        "link": "https://m.media-amazon.com/images/S/al-na-9d5791cf-3faf/c42d8d36-7440-4ebc-aecc-db53d8d85d12.mp4/productVideoOptimized.mp4",
        "thumbnail": "https://m.media-amazon.com/images/S/al-na-9d5791cf-3faf/c42d8d36-7440-4ebc-aecc-db53d8d85d12.mp4/r/THUMBNAIL_360P_FRAME_3_CAPTURE_2.JPG"
      },
      "rating": 5,
      "reviews": 5,
      "price": "$249.98",
      "extracted_price": 249.98
    },
    {
      "position": 3,
      "asin": "B08315PBM4",
      "title": "LEMBERI 48 Inch Heavy Duty Indestructible Dog Crate, Escape Proof Double Door Dog Kennel with Lockable Wheels, High Anxiety Extra Large Dog Cage Indoor Use, with Removable Tray",
      "link": "https://aax-us-east-retail-direct.amazon.com/x/c/JDEw3dT3vbDp67nz2sncuRQAAAGdgLgfpwEAAAH2AQBvbm9fdHhuX2JpZDUgICBvbm9fdHhuX2ltcDIgICCAb5Ac/clv1c_ek-YBfHXFbbWzjK3YkNvQ2gzXEu30oBD4TkhwfTK-9DJ6O9urVwSUIM9YjtofcvRpHZ_WQcWrnF50KOuHSghhne_hAsPyqqRD1hkjBWh1MNVDwH52EI5dy187OHs9tM8fiZviQ1MSDKLi_uZbk9fgsHPgF2aim3K2YwQrzchwK4NS9_FvQ63AK7gN4q5N9vS9e4nuQtMGATiGeb35wBG1nv_DU4uDTZU8EVQ4Yj6GvbtqiYPrBLEfPy2HXA1-MffZFpduZZtZ4Ii7aN7ivloRudoj9lAvbJVAh3sc07ZyfO3Kv4XmWHuqtMz20pfH07Rh6pKe8AlIVxmM_oYYFIuv6RqZGAlKPKz7ms0KVy8WHQcLWXXpen7Tmagse8vvWevof0Th3-NlGweTYjEdfPh1n6EQsT3G3XAxr5L1I69_NlBGkhr0Jd2-21oFQxNmVDz-raz2c4jT84ZsKFX4ShMAzqUlR7FMTu6DhsTTdRwEsVm8Y-fNgcAxB6FqajHv2FG-vNkPNQbwDHxrOHywg_qvL0PZN0QZ7kPTp0QyHZcJpZM4VPvzB3SN0jwH0jKm-yNXXlajDqV1Yvo5VA6fSzOylvJdhmzrkxkdfNj1D80BhFW7o4Kc89zid7y9iyogoOGWQ1GUEuodzRiXyqKvV32M_hNMivAWq2jGCoWeupGMW7XG-VZxzyK3y8TpEw_JZC6k-BsVogple752yLdSrTYt3natZr_SrPbEuj8J0jrx-voVMz9V9dfs4iTZB2nXzIi1GZEkg4CM7fp_Rmh1g6q8K6QeC6q1-Y4hOhBQx0NZhSQ_1goIf634PkCMbI2eDs7vPgd5X-TDhVkXrk9bxrBBGzw5rG7-EYYYBKjdGbhSVZX4a-Cm8u_pK4B8iCmGHs9r2N8OY_uZ_bnZzhB6Izf8LrNwm4eHiHz8BVPmSp_BEeJpeeL_6VtQzJp30E8q-ak1ZVdiixaDeyFrA232_t4Zm9Wqa1tGzY52mr3QVh4njwI2K-8FVhYF3u0VpH4IlvZYXWNuPCjS17T7nXiAueaOCB5Gko0523xccmwobjXiHmwvBcWlBf1uTTA9yyaBdaT60kdRLtrEzgaoHG2YamahiGqK1UvlAL8FUbXm-gyCzunHbLaFOrkZ_Y3a9faUchHk7nYxWe7BF6-887kNx1ibYUCYRjOdgQiTaKusDCaMVSfxyse58br3_KeC0aIQvZ2Cd9GfNQnORyFkhVd8vPkSVvxzs9IZ8SjJdPg7xHgaY9yuVqps1JQJmaMiZ1OphN1pjncmPjXbr7tkxKdwGodsQhjtzsEh3X4B9kffqYrjkdJPFmtwFTBQnm15IrQ3J7dk0UTnnkOgKSVU8CWjv89c0GcTLj7YAcJPwgS-tajv1R2yPE0wcKBhtqWGjY3sE0vNEUSc2EddMqsI93Kd3GhlfazNTEYij2Uy4OoBaDJnefyTD7DLlaChd4bgZ2QK229jZoHVw37DOrRnkyCoLl5xtlVLTvh9MCkRxK5u3aRgRiT1HZLVZyLHxHIOfMRfX033das/https://www.amazon.com/dp/B08315PBM4/?_encoding=UTF8&pd_rd_i=B08315PBM4&pd_rd_i=B08315PBM4&ref_=sbx_be_s_sparkle_ssd_cta&pd_rd_w=ypYD1&content-id=amzn1.sym.ccb770a9-35d1-4af6-8af2-bcbd12656fbb&pf_rd_p=ccb770a9-35d1-4af6-8af2-bcbd12656fbb&pf_rd_r=7G2FD7MKN8KHFEPRZ04K&pd_rd_wg=KY4uL&pd_rd_r=ab42157f-1806-47ab-81af-017f1ceb4f98",
      "link_clean": "https://www.amazon.com/dp/B08315PBM4/",
      "serpapi_link": "https://serpapi.com/search.json?amazon_domain=amazon.com&asin=B08315PBM4&device=desktop&engine=amazon_product",
      "thumbnail": "https://m.media-amazon.com/images/I/51+lqh0jkrL._AC_SR100,100_QL65_.jpg",
      "video": {
        "link": "https://m.media-amazon.com/images/S/al-na-9d5791cf-3faf/c2f7795d-0d9c-45cd-a5b6-815b23bc3435.mp4/productVideoOptimized.mp4",
        "thumbnail": "https://m.media-amazon.com/images/S/al-na-9d5791cf-3faf/c2f7795d-0d9c-45cd-a5b6-815b23bc3435.mp4/r/THUMBNAIL_360P_FRAME_3_CAPTURE_2.JPG"
      },
      "rating": 4.6,
      "reviews": 3937,
      "price": "$129.86",
      "extracted_price": 129.86
    },
    {
      "position": 4,
      "asin": "B0DZF3X8WC",
      "title": "SportPet Airline Compliant MEDIUM 24.25\" Travel Dog Kennel-Durable Plastic Airline Pet Carrier w/ Removable Wheels & Food Bowls, Collapsible Indoor/Outdoor Dog Kennel, Dogs up to 23\"L & 15\"H-Dark Gray",
      "link": "https://aax-us-east-retail-direct.amazon.com/x/c/JAxnvPHOwO2vZoYsePNWVE0AAAGdgLgfqAEAAAH2AQBvbm9fdHhuX2JpZDUgICBvbm9fdHhuX2ltcDIgICChGVH0/clv1c_ek-wBfHXUsbWHn2mJkKPYYizTwsq8EBEdJEVO3enjsZOnf9npk9gkHusUylgtRhr9XoqWA8Wqm050IO-UbQuMDEi5EHFbZvFJ4AxErTSHtQVzlJ0N_uuRbz54-xeElPm6Y1FX4TWT37CxB70qh3a_9K7IN6Wgi3MgPzoj5WpQAAZ1CmrjlCLvEPEdDwNLjca7uHq6lZXE6_4nswdZgSZNEFbv__fdUqtwf-m_W7t1875wRUxeCGa5LgeUX4e-Y-Qj0T3aFUUYMqMfFS3oUnqqfVGQrWvVgwlfgOMkYyo07CzJPKX2c1MhOkPfoYua1FJ5dPKl6SFRWXsJ-0qRz5EujM5ZvTVdfPEJIxF48wRrOKxGeipDQWuPaKqseDfxTqZk2R3UFA85IkZszpKBtJpL37LBEnLJY5VOL367AFerGxp-TgE8t29dp_bLTRXlBHr1duG3s2Pa_K3gB4yR-Y2bhohh6XJmamMycfv2WK6fIjB2b03bAQy4PqoSR5miE63uk8Md6SrKu6r2rFq10S4xJ4AGoHOIR2DomNg24adW8_Fgz0LNiFpyXTbFMhGTeJADnzXWcfiTSRx2cOJ3tJJ39zkeLYMa50L5hB1AVeZHTBPDkakRJP0MkBM_GmrPgg_XRk039RIW1hke0wvgVQgDkeSW59CRci3feSxw7KGzT3Snh9DqNap2cWxAni1q6UjnuQTAiUvyIXEyq0MCNog6wF7Hg4zGcT7NNn-FgdO4nNTDlpLAlLTRnby8GkGBok-z2eZI0-ulumSzpSaPt3-yIfQ6VIxc_T1gaU-or9YYtnBEo0n_Bur1yuT9JTaRcnD7M9S1e0f6BkL0ist73FGfG6h3FBGDsTYEk_GaGcbQFF2Kl28DupnTq63SWNLy3KDYnbFPeNR7G10vGKKg_b801MCyH8McaHJr8jKxmm-Us7cJpkJscXNGXb2eVbBm-kXOYnxAUTN7e_VkfrCGtTaDMniT10X-vNBG3-WZYWNW9K41CLUEbuIXsgSg6lupG3q39mAOsZJUHae6hhA1wDOKG01c9PGwOLxLApFK57NU-cogKaAgWnfYP7v340gOTPxAamBWYj2CoDfRT6c2oV2H86QsOURqaB26mR2ZVt1aQxqcN5VsVeR2KK1EghvJyrHdPa7FmARVefijBNOuaeUqqFxwwUVoXP8b-e3IUhgeTg0SIocTH_5qTEYTdknRkBI6fJG4AV55NCxcgwGcNBj4p8h8xqDpaFO_PMQqrt62L5ubve7-UTPM8KhlRtU4yFouK3CWvzomI2kU-aTnIF9lPbIjJB0OdLu5R-Y8aaJbFFw8LT1qSFgiD_TQzXjZ9e671dnWjq7ul7pDRYMwBesM-PAzPUuMZv9JKtYr3K4rxJkwEV1QrvEvR-VVOzQcz-DLDrCkTsx-Mq-2JiARq1d1FUnp1zXHQDPVX8qCM7tabS7kLAu8J7A5MWRDn8uNBWv3TMZuIjfEhS1IgTxwXl2t-iLIyah2kDBwQtCtM96chiLVE9qgZPgfVpqVcLncqk/https://www.amazon.com/dp/B0DZF3X8WC/?_encoding=UTF8&pd_rd_i=B0DZF3X8WC&pd_rd_i=B0DZF3X8WC&ref_=sbx_be_s_sparkle_ssd_cta&pd_rd_w=ypYD1&content-id=amzn1.sym.ccb770a9-35d1-4af6-8af2-bcbd12656fbb&pf_rd_p=ccb770a9-35d1-4af6-8af2-bcbd12656fbb&pf_rd_r=7G2FD7MKN8KHFEPRZ04K&pd_rd_wg=KY4uL&pd_rd_r=ab42157f-1806-47ab-81af-017f1ceb4f98",
      "link_clean": "https://www.amazon.com/dp/B0DZF3X8WC/",
      "serpapi_link": "https://serpapi.com/search.json?amazon_domain=amazon.com&asin=B0DZF3X8WC&device=desktop&engine=amazon_product",
      "thumbnail": "https://m.media-amazon.com/images/I/41sGc4TLvVL._AC_SR100,100_QL65_.jpg",
      "video": {
        "link": "https://m.media-amazon.com/images/S/al-na-9d5791cf-3faf/b7ba5903-efcb-47f1-895c-d1b3381d2847.mp4/productVideoOptimized.mp4",
        "thumbnail": "https://m.media-amazon.com/images/S/al-na-9d5791cf-3faf/b7ba5903-efcb-47f1-895c-d1b3381d2847.mp4/r/THUMBNAIL_360P_FRAME_3_CAPTURE_2.JPG"
      },
      "rating": 4.5,
      "reviews": 6147,
      "price": "$127.00",
      "extracted_price": 127
    },
    {
      "position": 5,
      "asin": "B0FRQCCVY3",
      "title": "Dog Crate Furniture Foldable with Dog Bed Mat, 27\" No Assembly Decorative Dog Kennel Indoor, Heavy Duty Small Collapsible Dog Crates for Small Dogs (Under 25 lb), Wooden Dog Cage",
      "link": "https://aax-us-east-retail-direct.amazon.com/x/c/JByQhvAkHplKa51-32YZ0lUAAAGdgLgfqQEAAAH2AQBvbm9fdHhuX2JpZDUgICBvbm9fdHhuX2ltcDIgICA5VyB8/clv1c_ek-YBXfWbcbSXg5XYzvi_kTD8ESxt6A52g-3rtr22lO7uc-vcwDtYasYLoX8JDm4X_GPR7tHL3TenzWPHYikljXCaouP3Pc_Z2MPexZMnk1m3rBJhCZOGmjQYnh9r4ChPVt8ffj5_Omw-rwpRAqvcHDboel8VlQj1MT3wm_-jCdd3GeCzLKplKZBGEoqqRlSojFbberLnAHBr-3sn-Bm1kOplZf3Dt-Cxepd_kz7GvbtOmTvJ1wkio6tClA1_MXfBgs2toeKn_7RDR4uhMFm5MmtjZtuklGpf8wi3MBwR_ryuPsSeJn5yTeyHAb3r3ve_7kEOMApIVxWMwVYYmsZzEB0D1RpChOJhJT4hHq0WEgcTHvbW5ySPy9un6u0k1EFAJd9pmpWuAwgTTqqBtLoPTZPoSUNE1bTanCskBM8lbvbDlHJ0OwMIEqbkTg5Rn_KYh1k5MoVe0bW--AnuVpFOmmcSkrs2FpeVMOXbQHblcJc0r8XzdMQ4rFNxA7qPRS7mIWkDyBBvRfNUxLDZuz4o1ONgWVljAUt8l0MTwsCNuZYdfU4wwzaFbQTzyNxiKBZoMuO2-KxOccr5j_sYF6_WDRzl33__NA2QN8gCu_NwqIeaWXOY_RE7--bAOJErPbdEjMyA3DJJlFi3yQXT0QXyOHEEAkEn2ONKhYORxk7jwjv1DN2NCYu2YNTCg2o32ytEQwHfr5t62c7ik78TppP2pOQXf8RKYGY4J_oynP2OyODLTPoqSlOsJm7PlX9raFRedkwP3KqwA6cGdd50YUa_6tLx-vDKo0N0x0a12tkdTGYamouqkmSZGh4OVkCPGn6Ruh8JbzYEKP46iLXWUBZAKDtqXjonPbA2Syv5rrsQcEI5emGoGT8DFjYlNYtXuysIVBEmDYAIXPpNo6AHyF4pZWWrZOQ_J3tMNMzRBLDw7ewXRd-5ZltTgeVybZEMato2BGMYmmvp452x-UoxAsaNibF3mWZiKONADBAQlOfZ4S7iClgWkkEqdgNQTEZ93Jtpf79Z-0DucVhWTQxUcRO4O51HBKwFoeu8NoQ-LBwWehSMdo6QO05R8wWGQl3dnO_6TAZ17CFDYVLOE1PR4RN15xgq3pYe-VMqdTkXDFjMqI8caWsqSbF00iqZbBgNiH-oESGMuaPa1Pk-369IvgWl5Eb_ZNgIX0P6DDVzAnxFmhLT8Z5U4AuSEGrv1LAnQMmu52m2qUgCu1xga97wMbEf43b8hc2r4siE-UKP6fMscVYtrjofEAoQN4f_qy6y5QqQ1hcLTRv-shMjHqFInAs0RgJOvJiS1JLzGLXMFzfHhD-a4bkvtqNQqmZ4GhQuIhkW5-jJGGWkDoLppe4E6NgdogpNzHGSNjBZshrnHDzKZm8QPF1uaj9n1RCU46wBSYz3p2NksO0RYh030UFQo8A28ogpauodNdJpZj1aXmNJxUDifxHyBoN1Oyefd37_-x0Aoa5togvpwLYE70RlW_2OkD_a6sLzKP0-IqxTtYmPRN9sxCnuu7aCDra_QLizhSpRA/https://www.amazon.com/dp/B0FRQCCVY3/?_encoding=UTF8&pd_rd_i=B0FRQCCVY3&pd_rd_i=B0FRQCCVY3&ref_=sbx_be_s_sparkle_ssd_cta&pd_rd_w=ypYD1&content-id=amzn1.sym.ccb770a9-35d1-4af6-8af2-bcbd12656fbb&pf_rd_p=ccb770a9-35d1-4af6-8af2-bcbd12656fbb&pf_rd_r=7G2FD7MKN8KHFEPRZ04K&pd_rd_wg=KY4uL&pd_rd_r=ab42157f-1806-47ab-81af-017f1ceb4f98",
      "link_clean": "https://www.amazon.com/dp/B0FRQCCVY3/",
      "serpapi_link": "https://serpapi.com/search.json?amazon_domain=amazon.com&asin=B0FRQCCVY3&device=desktop&engine=amazon_product",
      "thumbnail": "https://m.media-amazon.com/images/I/51ujwlTbzJL._AC_SR100,100_QL65_.jpg",
      "video": {
        "link": "https://m.media-amazon.com/images/S/al-na-9d5791cf-3faf/4a6d24e1-2643-4017-9545-64ff8b7baa8b.mp4/productVideoOptimized.mp4",
        "thumbnail": "https://m.media-amazon.com/images/S/al-na-9d5791cf-3faf/4a6d24e1-2643-4017-9545-64ff8b7baa8b.mp4/r/THUMBNAIL_360P_FRAME_3_CAPTURE_2.JPG"
      },
      "rating": 2.9,
      "reviews": 22,
      "price": "$119.99",
      "extracted_price": 119.99
    }
  ],
  "reviews_information": {
    "summary": {
      "text": "Customers find the dog crate to be of great quality and very easy to set up.",
      "insights": [
        {
          "title": "Quality",
          "sentiment": "positive",
          "mentions": {
            "total": 8,
            "positive": 8,
            "negative": 0
          },
          "summary": "Customers find the crate's quality excellent, with one mentioning it's great for car use.",
          "examples": [
            {
              "position": 1,
              "snippet": "Great crate but poor sales technique",
              "link": "https://www.amazon.com/gp/customer-reviews/R1OROR3D1XCFOZ"
            },
            {
              "position": 2,
              "snippet": "Great quality, be careful of measurements",
              "link": "https://www.amazon.com/gp/customer-reviews/R1K2U99YFN67GL"
            },
            {
              "position": 3,
              "snippet": "Love this crate! Easy to fold up and very portable. Bought this as a portable option for dog shows and class, and absolutely love it.",
              "link": "https://www.amazon.com/gp/customer-reviews/R2JF169R034GYN"
            },
            {
              "position": 4,
              "snippet": "...Love the design and quality. They weigh less than the wire crates of the same size.",
              "link": "https://www.amazon.com/gp/customer-reviews/REG6UEZOTMTGZ"
            }
          ]
        },
        {
          "title": "Easy to set up",
          "sentiment": "positive",
          "mentions": {
            "total": 6,
            "positive": 6,
            "negative": 0
          },
          "summary": "Customers find the dog crate easy to set up, with one mentioning it's simple to put up and take down.",
          "examples": [
            {
              "position": 1,
              "snippet": "...Easy to travel with, easy to put up and take down. The neutral colors of the crate matches anything....",
              "link": "https://www.amazon.com/gp/customer-reviews/R5SYAY59LZGCG"
            },
            {
              "position": 2,
              "snippet": "I love this crate. It was easy to put together (and I am not handy) and is sturdy....",
              "link": "https://www.amazon.com/gp/customer-reviews/R2R3A7NR8UV1V9"
            },
            {
              "position": 3,
              "snippet": "...The quality of the crate is awesome. Assembly was easy and it was sturdy enough. However the deminsions are misleading....",
              "link": "https://www.amazon.com/gp/customer-reviews/R1K2U99YFN67GL"
            },
            {
              "position": 4,
              "snippet": "Easy to set up & safe for the puppy.",
              "link": "https://www.amazon.com/gp/customer-reviews/RQAJNL5ZTY38K"
            }
          ]
        }
      ],
      "images": [
        "https://m.media-amazon.com/images/I/71obX4m6U-L.jpg",
        "https://m.media-amazon.com/images/I/61ayLrBHymL.jpg",
        "https://m.media-amazon.com/images/I/617mALmqR5L.jpg",
        "https://m.media-amazon.com/images/I/71RXKtqp+hL.jpg",
        "https://m.media-amazon.com/images/I/71uQLDg6zgL.jpg",
        "https://m.media-amazon.com/images/I/61hKzV3GosL.jpg",
        "https://m.media-amazon.com/images/I/61lsTFGeyLL.jpg",
        "https://m.media-amazon.com/images/I/71ZjOcc7dcL.jpg",
        "https://m.media-amazon.com/images/I/71IJfeRPFsL.jpg",
        "https://m.media-amazon.com/images/I/71piLJQGAbL.jpg",
        "https://m.media-amazon.com/images/I/71+Ywadd9GL.jpg",
        "https://m.media-amazon.com/images/I/71D9ZLicukL.jpg"
      ],
      "customer_reviews": {
        "5 star": 86,
        "4 star": 14,
        "3 star": 0,
        "2 star": 0,
        "1 star": 0
      }
    },
    "authors_reviews": [
      {
        "position": 1,
        "title": "Great design and easy to use!",
        "text": "What a great invention! These are very easy to set up and collapse. I like that they are self contained without any bags or straps to keep track of. My only wish is that there was an additional size in between the small and the large. My whippets fit, but they could use an extra inch all around for comfort. Love the design and quality. They weigh less than the wire crates of the same size.",
        "rating": 5,
        "date": "March 10, 2026",
        "author": "Vicki",
        "author_link": "https://www.amazon.com/gp/profile/amzn1.account.AFRYLGZQUZTR3LO3FIHTKKJ7KPRQ",
        "author_image": "https://m.media-amazon.com/images/S/amazon-avatars-global/default.png",
        "helpful_votes": "4 people found this helpful",
        "product": {
          "size": "27.96\"(L)X18.3\"(W)X20.87(H)"
        }
      },
      {
        "position": 2,
        "title": "Great cage with easy setup",
        "text": "Very solid? Easy to set up from place to place. Even the puppy seems to really like it. 😊",
        "rating": 5,
        "date": "February 17, 2026",
        "author": "Cliff Blizzard",
        "author_link": "https://www.amazon.com/gp/profile/amzn1.account.AFLBAL3OPZWNKWRULUL3M2TFGCPQ",
        "author_image": "https://m.media-amazon.com/images/S/amazon-avatars-global/39badaef-b9f7-468c-8b1e-a5a31f95c44a._CR0%2C0%2C1125%2C1125_SX460_.jpg",
        "helpful_votes": "3 people found this helpful",
        "product": {
          "size": "27.96\"(L)X18.3\"(W)X20.87(H)"
        }
      },
      {
        "position": 3,
        "title": "Great quality!",
        "text": "Awesome crate for my dog. Love that it collapses and I can take it anywhere. Great quality and very speedy shipping.",
        "rating": 5,
        "date": "March 27, 2026",
        "author": "Amazon Customer",
        "author_link": "https://www.amazon.com/gp/profile/amzn1.account.AF7VJNTZY7EXB2Y4IBFITUSP5WTQ",
        "author_image": "https://m.media-amazon.com/images/S/amazon-avatars-global/default.png",
        "helpful_votes": "2 people found this helpful",
        "product": {
          "size": "27.96\"(L)X18.3\"(W)X20.87(H)"
        }
      },
      {
        "position": 4,
        "title": "Great quality, be careful of measurements",
        "text": "I bought this collapible crate for my Australian Shepherd as an option to take to dog shows with us. The quality of the crate is awesome. Assembly was easy and it was sturdy enough. However the deminsions are misleading. I ended up having to return the crate because my dog couldn't stand or sit up at all and it wasn't easy for him toturn around in it. He measures the same size as the pictured Border Collie? But the dimensions are the outside deminsions of the crate. The inside measures smaller. I hope some vendor put there comes out with a solid (not soft-sided)collapible crate measuring 39\" L x 28\" H as that would be a perfect fit for my Aussie's measurements + the 2-4\" recommended for crates.",
        "rating": 4,
        "date": "March 31, 2026",
        "author": "Kathryn Smith",
        "author_link": "https://www.amazon.com/gp/profile/amzn1.account.AE64EEYVFNC4K6JHNHTL7TAFCQNQ",
        "author_image": "https://m.media-amazon.com/images/S/amazon-avatars-global/default.png",
        "helpful_votes": "2 people found this helpful",
        "product": {
          "size": "36.4\"(L)x22.84\"(W)25.8\"(H)"
        }
      },
      {
        "position": 5,
        "title": "Sturdy, Easy to Assemble",
        "text": "I love this crate. It was easy to put together (and I am not handy) and is sturdy. It doesn’t make a lot of noise when my pup comes into contact with it. I wish it came in one size smaller for my other smaller puppy. Perfect fit for my 4 month old, 12 lb cavapoo to grow into. I bought a medium pad from KindTails and put it in there and it’s a perfect fit. I don’t use it for travel, but it seems to me that it’ll collapse easily since it popped together so easily when assembled.",
        "rating": 5,
        "date": "February 25, 2026",
        "author": "GatorB8t",
        "author_link": "https://www.amazon.com/gp/profile/amzn1.account.AH6CSRKN3LZCOBCVZN34NUWT23JQ",
        "author_image": "https://m.media-amazon.com/images/S/amazon-avatars-global/default.png",
        "helpful_votes": "2 people found this helpful",
        "product": {
          "size": "27.96\"(L)X18.3\"(W)X20.87(H)"
        }
      },
      {
        "position": 6,
        "title": "Wonderful Crate",
        "text": "Fantastic popup crate. We have loved it for our new puppy. Our house is small and folding down will help a lot when it comes time to put it away. The 28\" size has been great for our large breed puppy (Bernese Mtn Dog) and it should last him a couple of months before he needs an upgrade.",
        "rating": 5,
        "date": "February 15, 2026",
        "author": "Sage and Stone Homestead",
        "author_link": "https://www.amazon.com/gp/profile/amzn1.account.AHTIJIBT6OBUMJIWCB55FV2374KQ",
        "author_image": "https://m.media-amazon.com/images/S/amazon-avatars-global/default.png",
        "helpful_votes": "One person found this helpful",
        "product": {
          "size": "27.96\"(L)X18.3\"(W)X20.87(H)"
        }
      },
      {
        "position": 7,
        "title": "Love this crate for class",
        "text": "Love this crate! Easy to fold up and very portable. Bought this as a portable option for dog shows and class, and absolutely love it.",
        "rating": 5,
        "date": "February 24, 2026",
        "author": "Cat Hugger in MI",
        "author_link": "https://www.amazon.com/gp/profile/amzn1.account.AH6WXSL7HTMMRHRGQO2JXSOQCJ5Q",
        "author_image": "https://m.media-amazon.com/images/S/amazon-avatars-global/50336d8e-1b85-41ff-bff3-cc4056eba3f0._CR62%2C0%2C375%2C375_SX460_.jpg",
        "helpful_votes": "One person found this helpful",
        "product": {
          "size": "36.4\"(L)x22.84\"(W)25.8\"(H)"
        }
      },
      {
        "position": 8,
        "title": "Stylish Dog Crate",
        "text": "Easy to set up & safe for the puppy.",
        "rating": 5,
        "date": "March 2, 2026",
        "author": "Anita M Viehmann",
        "author_link": "https://www.amazon.com/gp/profile/amzn1.account.AEZQBJKFJ4OSXY2LUEJ3DKHEDTEQ",
        "author_image": "https://m.media-amazon.com/images/S/amazon-avatars-global/default.png",
        "helpful_votes": "One person found this helpful",
        "product": {
          "size": "27.96\"(L)X18.3\"(W)X20.87(H)"
        }
      }
    ],
    "other_countries_reviews": [
      {
        "position": 1,
        "title": "Soddisfatta",
        "text": "Ottimo prodotto",
        "rating": 5,
        "date": "March 29, 2026",
        "author": "Concetta",
        "author_image": "https://m.media-amazon.com/images/S/amazon-avatars-global/default.png",
        "product": {
          "size": "36.4\"(L)x22.84\"(W)25.8\"(H)"
        },
        "country": {
          "code": "IT",
          "name": "Italy"
        },
        "language": {
          "code": "it",
          "name": "Italian (Italy)"
        }
      },
      {
        "position": 2,
        "title": "Bigger than expected",
        "text": "Houseworthy good looking cage. sturdy and well made.Would help if the cage could have a back opening to straighten the bedding as this cage is quite long. however very pleased and impressed by this item and the dog is very happy to be in it when necessary;",
        "rating": 5,
        "date": "March 14, 2026",
        "author": "mike W",
        "author_image": "https://m.media-amazon.com/images/S/amazon-avatars-global/default.png",
        "product": {
          "size": "36.4\"(L)x22.84\"(W)25.8\"(H)"
        }
      },
      {
        "position": 3,
        "title": "Crate",
        "text": "Very roomy",
        "rating": 5,
        "date": "March 27, 2026",
        "author": "wander",
        "author_image": "https://m.media-amazon.com/images/S/amazon-avatars-global/default.png",
        "product": {
          "size": "27.96\"(L)X18.3\"(W)X20.87(H)"
        }
      }
    ]
  }
}